README
setup.py
supermutes/__init__.py
supermutes/base.py
supermutes/decorators.py
supermutes/dot.py
supermutes/example.py
supermutes/ordered.py
supermutes/readonly.py
supermutes/register.py
supermutes.egg-info/PKG-INFO
supermutes.egg-info/SOURCES.txt
supermutes.egg-info/dependency_links.txt
supermutes.egg-info/top_level.txt
supermutes.egg-info/zip-safe