Metadata-Version: 1.1
Name: supermutes
Version: 0.2.5
Summary: A collection of super mutables
Home-page: https://github.com/alexcouper/supermutes
Author: Alex Couper
Author-email: info@alexcouper.com
License: UNKNOWN
Platform: UNKNOWN
Classifier: Development Status :: 4 - Beta
Classifier: Intended Audience :: Developers
Classifier: License :: OSI Approved :: GNU Library or Lesser General Public License (LGPL)
Classifier: Operating System :: OS Independent
Classifier: Programming Language :: Python :: 2.6
Classifier: Programming Language :: Python :: 2.7
Classifier: Programming Language :: Python :: 3
Classifier: Topic :: Software Development :: Libraries :: Python Modules
